LICENSE.txt
Quick_start_guide_Py_BANSHEE.pdf
README.md
graphviz_error.txt
setup.cfg
setup.py
examples/Concrete_vehicle_bridge_column.csv
examples/Samp_based_Case_6.csv
examples/UNINET_BN_Rank_corr_mat.txt
examples/cities.csv
examples/example_0.py
examples/example_1.py
examples/example_2.py
examples/example_3.py
py_banshee/__init__.py
py_banshee/bn_plot.py
py_banshee/copula_test.py
py_banshee/d_cal.py
py_banshee/prediction.py
py_banshee/rankcorr.py
py_banshee/sample_bn.py
py_banshee.egg-info/PKG-INFO
py_banshee.egg-info/SOURCES.txt
py_banshee.egg-info/dependency_links.txt
py_banshee.egg-info/requires.txt
py_banshee.egg-info/top_level.txt
py_banshee/__pycache__/__init__.cpython-38.pyc
py_banshee/__pycache__/bn_plot.cpython-38.pyc
py_banshee/__pycache__/copula_test.cpython-38.pyc
py_banshee/__pycache__/d_cal.cpython-38.pyc
py_banshee/__pycache__/prediction.cpython-38.pyc
py_banshee/__pycache__/rankcorr.cpython-38.pyc
py_banshee/__pycache__/sample_bn.cpython-38.pyc