Metadata-Version: 2.1
Name: py_banshee
Version: 1.1.2
Summary: Py_Banshee allows for quantifying non-parametric Bayesian Networks
Home-page: https://github.com/mike-mendoza/py_banshee
Download-URL: https://github.com/mike-mendoza/py_banshee/archive/refs/tags/v1.1.2.tar.gz
Author: Paul Koot, Miguel Angel Mendoza Lugo, Oswaldo Morales Napoles
Author-email: mendozalugo@gmail.com
License: GNU
Project-URL: Bug Tracker, https://github.com/mike-mendoza/py_banshee/issues
Keywords: pypi,py_banshee,tutorial
Classifier: Development Status :: 3 - Alpha
Classifier: Intended Audience :: Developers
Classifier: Topic :: Software Development :: Documentation
Classifier: License :: OSI Approved :: GNU General Public License v3 (GPLv3)
Classifier: Programming Language :: Python :: 3
Classifier: Programming Language :: Python :: 3.7
Classifier: Programming Language :: Python :: 3.8
Classifier: Programming Language :: Python :: 3.9
License-File: LICENSE.txt
Requires-Dist: ipython
Requires-Dist: pingouin
Requires-Dist: graphviz
Requires-Dist: pydot
Requires-Dist: pycopula
Requires-Dist: argparse
Requires-Dist: scipy
Requires-Dist: numpy
Requires-Dist: pandas
Requires-Dist: matplotlib
Requires-Dist: seaborn
Requires-Dist: networkx
